{
  "lastBackupTime": "2026-06-29T07:30:00.336Z",
  "backupStatus": "Success",
  "replicationStatus": "Replicated to region ap-south-2 (Cross-Region Sync)",
  "lastVerificationTime": "2026-06-29T07:30:00.336Z",
  "verificationStatus": "Passed",
  "recoveryTestLogs": [
    {
      "timestamp": "2026-06-29T07:30:00.317Z",
      "testType": "Automated RTO Verification Job",
      "status": "Success",
      "durationMs": 149,
      "rtoAchieved": "269ms (Target: <1 Hour)",
      "notes": "Active standby DB replication verification passed. Primary node connection healthy."
    },
    {
      "timestamp": "2026-06-29T06:30:00.271Z",
      "testType": "Automated RTO Verification Job",
      "status": "Success",
      "durationMs": 155,
      "rtoAchieved": "275ms (Target: <1 Hour)",
      "notes": "Active standby DB replication verification passed. Primary node connection healthy."
    },
    {
      "timestamp": "2026-06-29T05:30:00.271Z",
      "testType": "Automated RTO Verification Job",
      "status": "Success",
      "durationMs": 151,
      "rtoAchieved": "271ms (Target: <1 Hour)",
      "notes": "Active standby DB replication verification passed. Primary node connection healthy."
    },
    {
      "timestamp": "2026-06-29T04:30:00.273Z",
      "testType": "Automated RTO Verification Job",
      "status": "Success",
      "durationMs": 140,
      "rtoAchieved": "260ms (Target: <1 Hour)",
      "notes": "Active standby DB replication verification passed. Primary node connection healthy."
    },
    {
      "timestamp": "2026-06-29T03:30:01.329Z",
      "testType": "Automated RTO Verification Job",
      "status": "Success",
      "durationMs": 1175,
      "rtoAchieved": "1295ms (Target: <1 Hour)",
      "notes": "Active standby DB replication verification passed. Primary node connection healthy."
    },
    {
      "timestamp": "2026-06-28T19:30:00.259Z",
      "testType": "Automated RTO Verification Job",
      "status": "Success",
      "durationMs": 172,
      "rtoAchieved": "292ms (Target: <1 Hour)",
      "notes": "Active standby DB replication verification passed. Primary node connection healthy."
    },
    {
      "timestamp": "2026-06-28T14:30:02.580Z",
      "testType": "Automated RTO Verification Job",
      "status": "Success",
      "durationMs": 2496,
      "rtoAchieved": "2616ms (Target: <1 Hour)",
      "notes": "Active standby DB replication verification passed. Primary node connection healthy."
    },
    {
      "timestamp": "2026-06-27T19:30:01.261Z",
      "testType": "Automated RTO Verification Job",
      "status": "Success",
      "durationMs": 1159,
      "rtoAchieved": "1279ms (Target: <1 Hour)",
      "notes": "Active standby DB replication verification passed. Primary node connection healthy."
    },
    {
      "timestamp": "2026-06-27T18:30:01.205Z",
      "testType": "Automated RTO Verification Job",
      "status": "Success",
      "durationMs": 1105,
      "rtoAchieved": "1225ms (Target: <1 Hour)",
      "notes": "Active standby DB replication verification passed. Primary node connection healthy."
    },
    {
      "timestamp": "2026-06-27T17:30:00.239Z",
      "testType": "Automated RTO Verification Job",
      "status": "Success",
      "durationMs": 163,
      "rtoAchieved": "282ms (Target: <1 Hour)",
      "notes": "Active standby DB replication verification passed. Primary node connection healthy."
    }
  ]
}